mb_nlp/__init__.py
mb_nlp/classifier.py
mb_nlp/version.py
mb_nlp/classifier/__init__.py
mb_nlp/classifier/bert.py
mb_nlp/data/__init__.py
mb_nlp/data/dataset.py
mb_nlp/modernbert_multilabel/__init__.py
mb_nlp/modernbert_multilabel/model.py
mb_nlp/utils/__init__.py
mb_nlp/utils/helpers.py
mb_nlp-1.0.4.dist-info/METADATA
mb_nlp-1.0.4.dist-info/WHEEL
mb_nlp-1.0.4.dist-info/top_level.txt
mb_nlp-1.0.4.dist-info/RECORD
