Metadata-Version: 2.4
Name: mb_nlp
Version: 1.0.4
Summary: NLP text classification with BERT
Author: ['Malav Bateriwala']
Requires-Python: >=3.8
Requires-Dist: transformers>=4.38.0
Requires-Dist: torch>=2.0.0
Requires-Dist: pandas
Requires-Dist: scikit-learn
Dynamic: author
Dynamic: requires-dist
Dynamic: requires-python
Dynamic: summary
